{
  "url": "https://finance.yahoo.com/markets/article/lucid-stock-pops-on-new-ceo-fresh-funding-from-saudi-pif-uber-131046857.html",
  "title": "Lucid stock pops on new CEO, fresh funding from Saudi PIF, Uber",
  "published_at": "2026-04-15T00:00:00Z",
  "scraped_at": "2026-05-15T12:00:00Z",
  "text": "Lucid revealed it will receive $750 million in new investment from PIF and Uber, supporting the company as it ramps up Gravity SUV production and develops its upcoming midsize EV. As part of the agreement with Uber, the company increased its purchase commitment to at least 35,000 Lucid vehicles designed exclusively for Uber's robotaxi service, with Uber committing an additional $200 million investment to raise its total investments to $550 million. The new CEO appointment and expanded Uber partnership signaled a strategic pivot for Lucid toward robotaxi applications and further diversified funding sources.",
  "topic": "LCID",
  "source_type": "news_scraper.LCID"
}
