{
  "url": "https://nasdaq.com/articles/penny-stock-lucid-lcid-receives-1b-boost-from-saudi-arabias-pif",
  "title": "Penny Stock Lucid (LCID) Receives $1B Boost from Saudi Arabia's PIF",
  "published_at": "2024-10-30T00:00:00Z",
  "scraped_at": "2026-05-15T12:00:00Z",
  "text": "Lucid received $1.03 billion investment from Saudi Arabia's PIF through share purchases at $2.59 per share in October 2024. The investment supported stock price amid market pressures. PIF purchased approximately 396 million LCID shares demonstrating continued commitment. The investment extended company liquidity runway and signaled confidence in long-term business plan.",
  "topic": "LCID",
  "source_type": "news_scraper.LCID"
}
