{
  "url": "https://finance.yahoo.com/news/array-technologies-inc-arry-q2-220721423.html",
  "title": "Array Technologies Inc Q2 2024 Earnings Results",
  "published_at": "2024-08-08T00:00:00Z",
  "scraped_at": "2026-05-16T00:00:00Z",
  "text": "Array Technologies reported Q2 2024 earnings per share of $0.17, beating consensus estimates of $0.14. Revenue totaled $255.77 million, up 11% from consensus estimate of $230 million. Adjusted gross margin reached 35%, reflecting strong operational execution. Adjusted EBITDA reached $55.4 million. Despite positive earnings beat, company issued reduced guidance for full year 2024 due to project timing delays and macroeconomic headwinds. Management noted that project delays in Q2 appear to be primarily timing-related rather than cancellations, with 80% of order book scheduled for delivery between mid-2024 and year-end 2025. Company maintains strong liquidity with cash reserves and undrawn credit facilities totaling approximately $435 million.",
  "topic": "ARRY",
  "source_type": "news_scraper.ARRY"
}