{
  "url": "https://www.oracle.com/news/announcement/oracle-borderplex-and-bloom-energy-to-power-project-jupiter-with-fuel-cell-technology-2026-04-27/",
  "title": "Oracle, BorderPlex, and Bloom Energy to Power Project Jupiter with Fuel Cell Technology",
  "published_at": "2026-04-27T00:00:00Z",
  "scraped_at": "2026-05-16T00:00:00Z",
  "text": "Oracle and BorderPlex Digital Assets announced Project Jupiter will utilize Bloom Energy fuel cells to fully power the AI data center campus in Doña Ana County, New Mexico, supported by up to 2.45 GW of installed Bloom fuel cell capacity. This updated power design will replace Project Jupiter's previously planned gas turbines and diesel generators and consolidate the facility into one single microgrid campus. Under a master services agreement, Oracle intends to procure up to 2.8 gigawatts of Bloom's fuel cell systems, with an initial 1.2 GW of capacity contracted and deployment underway continuing into next year. Bloom's fuel cells will support Oracle projects in the U.S. and help meet demand for its cutting-edge cloud infrastructure. The partnership represents a significant vote of confidence in Bloom's technology as the solution for powering next-generation AI data center infrastructure. Oracle's stock jumped more than 4% on the announcement as the company broadened its capacity deal with Bloom Energy, while Bloom shares soared 22%.",
  "topic": "BE",
  "source_type": "news_scraper.BE"
}
