{
  "url": "https://www.zacks.com/stock/research/PYPL/price-target-stock-forecast",
  "title": "PayPal PYPL Stock Price Target And Forecast Analysis",
  "published_at": "2026-05-01T00:00:00Z",
  "scraped_at": "2026-05-16T12:00:00Z",
  "text": "Zacks provides comprehensive stock price targets and forecasts for PayPal Holdings. Consensus rating remains Hold. Analysts maintain cautious views given macro uncertainty. Forward earnings estimates reflect mid-single-digit EPS growth. Revenue growth forecast in low-to-mid single-digit range. Key metrics monitored include payment volume growth, transaction margin dollars, operating margin expansion, and free cash flow generation.",
  "topic": "PYPL",
  "source_type": "news_scraper.PYPL"
}
