{
  "url": "https://csimarket.com/stocks/compet_glance.php?code=ENPH",
  "title": "Enphase Energy Market Share and Competitive Position",
  "published_at": null,
  "scraped_at": "2026-05-16T00:00:00Z",
  "text": "Enphase Energy is largest inverter supplier for residential solar in U.S. with growing international share. As of 2022, Enphase held approximately 78% microinverter segment market share. In broader market, Enphase and SolarEdge hold 48% and 40% U.S. market respectively totaling 95% global inverter market share. Biggest competitors are SolarEdge and together they dominate solar inverter space. Other players include Huawei Technologies, Sungrow, TBEA and SMA Solar Technology. ENPH pioneered microinverters producing 5-15% more energy compared to string inverters reducing cost for homeowners. ENPH maintains strong pricing power despite temporary headwinds due to superior value proposition and strong balance sheet. Solar PV inverter market characterized by intense competition driven by rapid technological advancement, price sensitivity and evolving grid requirements with players competing on efficiency, durability, software capabilities and energy storage and smart grid integration.",
  "topic": "ENPH",
  "source_type": "news_scraper.ENPH"
}
