{
  "url": "https://tradestie.com/stocks/woof/buy-or-sell-now/",
  "title": "WOOF Buy or Sell? AI Score: 52/100 (HOLD Rating)",
  "published_at": null,
  "scraped_at": "2026-05-16T20:35:00Z",
  "text": "WOOF Buy or Sell Analysis. Current Rating: HOLD with AI Score of 52/100. Analyst Consensus: Based on analysis of 17 Wall Street analysts, WOOF has a neutral consensus with a median price target of $3.50 (ranging from $2.30 to $4.53). This outlook is supported by 2 Buy, 8 Hold, and 2 Sell ratings. Technical Outlook: Technically, WOOF is in an uptrend, with the price currently testing key support at $2.45. WOOF shows mixed signals with a HOLD rating - fine to hold existing positions but not urgent to buy or sell. Investor Sentiment Factors: WOOF experienced bullish movement possibly due to positive second-quarter financial results and raised earnings outlook in the pet industry. Improvement in GAAP net income and commitment to enhancing retail operations positively impacting investor sentiment. Growth Outlook: The company expects sales in 2026 to be flat to up 1.5%, a turnaround from a 2.5% decrease in revenue last year.",
  "topic": "WOOF",
  "source_type": "news_scraper.WOOF"
}
